cloud/__init__.py
cloud/aws.py
cloud/pusher.py
cloud/asyncbotocore/__init__.py
cloud/asyncbotocore/args.py
cloud/asyncbotocore/client.py
cloud/asyncbotocore/config.py
cloud/asyncbotocore/endpoint.py
cloud/asyncbotocore/paginate.py
cloud/asyncbotocore/session.py
cloud/utils/__init__.py
cloud/utils/s3.py
cloud/utils/version.py
pulsar_cloud-0.5.5.data/scripts/s3upload.py
pulsar_cloud-0.5.5.dist-info/DESCRIPTION.rst
pulsar_cloud-0.5.5.dist-info/LICENSE.txt
pulsar_cloud-0.5.5.dist-info/METADATA
pulsar_cloud-0.5.5.dist-info/RECORD
pulsar_cloud-0.5.5.dist-info/WHEEL
pulsar_cloud-0.5.5.dist-info/metadata.json
pulsar_cloud-0.5.5.dist-info/top_level.txt
