Metadata-Version: 2.0
Name: pulsar-cloud
Version: 0.5.5
Summary: Asynchronous clients for AWS and Pusher
Home-page: https://github.com/quantmind/pulsar-cloud
Author: Luca Sbardella
Author-email: luca@quantmind.com
License: BSD
Platform: UNKNOWN
Classifier: Development Status :: 3 - Alpha
Classifier: Environment :: Plugins
Classifier: Intended Audience :: Developers
Classifier: License :: OSI Approved :: BSD License
Classifier: Operating System :: OS Independent
Classifier: Programming Language :: Python
Classifier: Programming Language :: Python :: 3
Classifier: Programming Language :: Python :: 3.5
Classifier: Programming Language :: Python :: 3.6
Classifier: Topic :: Utilities
Requires-Dist: botocore (>=1.4.62)
Requires-Dist: greenlet
Requires-Dist: pulsar
